SETMOKE_API/SETMOKE_API.py
SETMOKE_API/__init__.py
SETMOKE_API/retrievel/GooglePlus.py
SETMOKE_API/retrievel/Post.py
SETMOKE_API/retrievel/Twitter.py
SETMOKE_API/retrievel/User.py
SETMOKE_API/retrievel/__init__.py
SETMOKE_API/util/ConfigurationParser.py
SETMOKE_API/util/__init__.py
SETMOKE_API-2.0.dist-info/METADATA
SETMOKE_API-2.0.dist-info/WHEEL
SETMOKE_API-2.0.dist-info/top_level.txt
SETMOKE_API-2.0.dist-info/RECORD
